pretalx_media_ccc_de/__init__.py
pretalx_media_ccc_de/apps.py
pretalx_media_ccc_de/forms.py
pretalx_media_ccc_de/models.py
pretalx_media_ccc_de/recording.py
pretalx_media_ccc_de/signals.py
pretalx_media_ccc_de/tasks.py
pretalx_media_ccc_de/urls.py
pretalx_media_ccc_de/views.py
pretalx_media_ccc_de/locale/django.pot
pretalx_media_ccc_de/locale/ar/LC_MESSAGES/django.mo
pretalx_media_ccc_de/locale/ar/LC_MESSAGES/django.po
pretalx_media_ccc_de/locale/bg/LC_MESSAGES/django.mo
pretalx_media_ccc_de/locale/bg/LC_MESSAGES/django.po
pretalx_media_ccc_de/locale/ca/LC_MESSAGES/django.mo
pretalx_media_ccc_de/locale/ca/LC_MESSAGES/django.po
pretalx_media_ccc_de/locale/cs/LC_MESSAGES/django.mo
pretalx_media_ccc_de/locale/cs/LC_MESSAGES/django.po
pretalx_media_ccc_de/locale/de_DE/LC_MESSAGES/django.mo
pretalx_media_ccc_de/locale/de_DE/LC_MESSAGES/django.po
pretalx_media_ccc_de/locale/de_DE/de/LC_MESSAGES/django.po
pretalx_media_ccc_de/locale/de_Formal/LC_MESSAGES/django.mo
pretalx_media_ccc_de/locale/de_Formal/LC_MESSAGES/django.po
pretalx_media_ccc_de/locale/el/LC_MESSAGES/django.mo
pretalx_media_ccc_de/locale/el/LC_MESSAGES/django.po
pretalx_media_ccc_de/locale/es/LC_MESSAGES/django.mo
pretalx_media_ccc_de/locale/es/LC_MESSAGES/django.po
pretalx_media_ccc_de/locale/es_MX/LC_MESSAGES/django.mo
pretalx_media_ccc_de/locale/es_MX/LC_MESSAGES/django.po
pretalx_media_ccc_de/locale/fr_FR/LC_MESSAGES/django.mo
pretalx_media_ccc_de/locale/fr_FR/LC_MESSAGES/django.po
pretalx_media_ccc_de/locale/id/LC_MESSAGES/django.mo
pretalx_media_ccc_de/locale/id/LC_MESSAGES/django.po
pretalx_media_ccc_de/locale/it/LC_MESSAGES/django.mo
pretalx_media_ccc_de/locale/it/LC_MESSAGES/django.po
pretalx_media_ccc_de/locale/ja_JP/LC_MESSAGES/django.mo
pretalx_media_ccc_de/locale/ja_JP/LC_MESSAGES/django.po
pretalx_media_ccc_de/locale/ko/LC_MESSAGES/django.mo
pretalx_media_ccc_de/locale/ko/LC_MESSAGES/django.po
pretalx_media_ccc_de/locale/nl/LC_MESSAGES/django.mo
pretalx_media_ccc_de-1.5.0.dist-info/licenses/LICENSE
pretalx_media_ccc_de-1.5.0.dist-info/METADATA
pretalx_media_ccc_de-1.5.0.dist-info/WHEEL
pretalx_media_ccc_de-1.5.0.dist-info/entry_points.txt
pretalx_media_ccc_de-1.5.0.dist-info/top_level.txt
pretalx_media_ccc_de-1.5.0.dist-info/RECORD
