Metadata-Version: 2.4
Name: pretalx-media-ccc-de
Version: 1.5.0
Summary: Pull recordings from media.ccc.de and embed them in talk pages.
Author-email: Tobias Kunze <r@rixx.de>
Maintainer-email: Tobias Kunze <r@rixx.de>
License: Apache Software License
Project-URL: homepage, https://github.com/pretalx/pretalx-media-ccc-de
Project-URL: repository, https://github.com/pretalx/pretalx-media-ccc-de.git
Keywords: pretalx
License-File: LICENSE
Dynamic: license-file
